shadowflake/__init__.py
shadowflake/__main__.py
shadowflake/shadowflake.py
shadowflake-1.0.0.dist-info/licenses/LICENSE
shadowflake-1.0.0.dist-info/METADATA
shadowflake-1.0.0.dist-info/WHEEL
shadowflake-1.0.0.dist-info/entry_points.txt
shadowflake-1.0.0.dist-info/top_level.txt
shadowflake-1.0.0.dist-info/RECORD
