Metadata-Version: 2.4
Name: shadowflake
Version: 1.0.0
Summary: A Python implementation of the Shadowflake UXID format!
Author-email: ItsThatOneJack <jack@ito.dev>
License-Expression: AGPL-3.0-or-later
Project-URL: Homepage, https://github.com/itsthatonejack-dev/shadowflake
Project-URL: Repository, https://github.com/itsthatonejack-dev/shadowflake
Project-URL: Issues, https://github.com/itsthatonejack-dev/shadowflake/issues
Keywords: uuid,uxid,identifier,shadowflake
Classifier: Development Status :: 4 - Beta
Classifier: Intended Audience :: Developers
Classifier: Programming Language :: Python :: 3
Classifier: Programming Language :: Python :: 3.10
Classifier: Programming Language :: Python :: 3.11
Classifier: Programming Language :: Python :: 3.12
Requires-Python: >=3.10
License-File: LICENSE
Provides-Extra: fancy
Requires-Dist: rich>=13.0.0; extra == "fancy"
Dynamic: license-file
